torchplasma/__init__.py
torchplasma/version.py
torchplasma/blending/__init__.py
torchplasma/blending/light.py
torchplasma/blending/overlay.py
torchplasma/conversion/__init__.py
torchplasma/conversion/lab.py
torchplasma/conversion/srgb.py
torchplasma/conversion/xyy.py
torchplasma/conversion/xyz.py
torchplasma/conversion/yuv.py
torchplasma/curves/__init__.py
torchplasma/curves/discrete.py
torchplasma/curves/lut.py
torchplasma/curves/natural.py
torchplasma/filters/__init__.py
torchplasma/filters/bilateral.py
torchplasma/filters/box.py
torchplasma/filters/gaussian.py
torchplasma/filters/guided.py
torchplasma/filters/log.py
torchplasma/gradients/__init__.py
torchplasma/gradients/horizontal.py
torchplasma/gradients/radial.py
torchplasma/gradients/vertical.py
torchplasma/linear/__init__.py
torchplasma/linear/chromaticity.py
torchplasma/linear/pointwise.py
torchplasma/linear/selective.py
torchplasma/linear/spectral.py
torchplasma/spatial/__init__.py
torchplasma/spatial/pointwise.py
torchplasma-0.0.1.dist-info/LICENSE
torchplasma-0.0.1.dist-info/METADATA
torchplasma-0.0.1.dist-info/WHEEL
torchplasma-0.0.1.dist-info/top_level.txt
torchplasma-0.0.1.dist-info/RECORD
