Metadata-Version: 2.1
Name: torchplasma
Version: 0.0.1
Summary: Differentiable image editing operations for computational photography in PyTorch.
Home-page: https://github.com/hdkai/Plasma
Author: Yusuf Olokoba
Author-email: hi@hdk.ai
License: Apache License 2.0
Platform: UNKNOWN
Classifier: Programming Language :: Python :: 3
Classifier: License :: OSI Approved :: Apache Software License
Classifier: Operating System :: OS Independent
Classifier: Topic :: Scientific/Engineering :: Image Recognition
Classifier: Topic :: Software Development :: Libraries
Requires-Python: >=3.6
Requires-Dist: imageio
Requires-Dist: torch
Requires-Dist: torchvision
